paypal_server_sdk-2.2.0.dist-info/licenses/LICENSE
paypalserversdk/__init__.py
paypalserversdk/api_helper.py
paypalserversdk/configuration.py
paypalserversdk/paypal_serversdk_client.py
paypalserversdk/controllers/__init__.py
paypalserversdk/controllers/base_controller.py
paypalserversdk/controllers/o_auth_authorization_controller.py
paypalserversdk/controllers/orders_controller.py
paypalserversdk/controllers/payments_controller.py
paypalserversdk/controllers/subscriptions_controller.py
paypalserversdk/controllers/transaction_search_controller.py
paypalserversdk/controllers/vault_controller.py
paypalserversdk/exceptions/__init__.py
paypalserversdk/exceptions/api_exception.py
paypalserversdk/exceptions/default_error_exception.py
paypalserversdk/exceptions/error_exception.py
paypalserversdk/exceptions/o_auth_provider_exception.py
paypalserversdk/exceptions/search_error_exception.py
paypalserversdk/exceptions/subscription_error_exception.py
paypalserversdk/http/__init__.py
paypalserversdk/http/api_response.py
paypalserversdk/http/http_call_back.py
paypalserversdk/http/http_client_provider.py
paypalserversdk/http/http_method_enum.py
paypalserversdk/http/http_request.py
paypalserversdk/http/http_response.py
paypalserversdk/http/proxy_settings.py
paypalserversdk/http/auth/__init__.py
paypalserversdk/http/auth/o_auth_2.py
paypalserversdk/logging/__init__.py
paypalserversdk/logging/sdk_logger.py
paypalserversdk/logging/configuration/__init__.py
paypalserversdk/logging/configuration/api_logging_configuration.py
paypalserversdk/models/__init__.py
paypalserversdk/models/activate_subscription_request.py
paypalserversdk/models/activity_timestamps.py
paypalserversdk/models/address.py
paypalserversdk/models/amount_breakdown.py
paypalserversdk/models/amount_with_breakdown.py
paypalserversdk/models/app_switch_context.py
paypalserversdk/models/apple_pay_attributes.py
paypalserversdk/models/apple_pay_attributes_response.py
paypalserversdk/models/apple_pay_card.py
paypalserversdk/models/apple_pay_card_response.py
paypal_server_sdk-2.2.0.dist-info/METADATA
paypal_server_sdk-2.2.0.dist-info/WHEEL
paypal_server_sdk-2.2.0.dist-info/top_level.txt
paypal_server_sdk-2.2.0.dist-info/RECORD
