Metadata-Version: 2.4
Name: paypal-server-sdk
Version: 2.2.0
Summary: PayPal's SDK for interacting with the REST APIs
Project-URL: Homepage, https://github.com/paypal/PayPal-Python-Server-SDK
Requires-Python: >=3.7
License-File: LICENSE
Requires-Dist: apimatic-core>=0.2.24,~=0.2.0
Requires-Dist: apimatic-core-interfaces>=0.1.8,~=0.1.0
Requires-Dist: apimatic-requests-client-adapter>=0.1.10,~=0.1.0
Requires-Dist: python-dotenv<2.0,>=0.21
Provides-Extra: testutils
Requires-Dist: pytest>=7.2.2; extra == "testutils"
Dynamic: license-file
